fifo_sync.v
module fifo_sync #(
  parameter DATA_WIDTH = 8,
  parameter DEPTH = 16,
  parameter ADDR_WIDTH = 4 // log2(DEPTH)
)(
  input wire clk,
  input wire rst,

  input wire wr_en,
  input wire rd_en,
  input wire [DATA_WIDTH-1:0] din,

  output reg [DATA_WIDTH-1:0] dout,
  output reg full,
  output reg empty
);

  // ✅ FIFO Memory Array —> Storage is sequential
  reg [DATA_WIDTH-1:0] fifo_mem [0:DEPTH-1];

  // ✅ Pointers and Counter —> Sequential registers
  reg [ADDR_WIDTH-1:0] write_ptr, read_ptr;
  reg [ADDR_WIDTH:0] count;  // Stores occupancy — sequential

  // ✅ Write Logic —> Updates write_ptr & storage synchronously
  always @(posedge clk) begin
    if (rst) begin
      write_ptr <= 0;
    end else if (wr_en && !full) begin
      fifo_mem[write_ptr] <= din;   // Write data into storage
      write_ptr <= write_ptr + 1;   // Advance write pointer
    end
  end

  // ✅ Read Logic —> Updates read_ptr & output synchronously
  always @(posedge clk) begin
    if (rst) begin
      dout <= 0;
      read_ptr <= 0;
    end else if (rd_en && !empty) begin
      dout <= fifo_mem[read_ptr];   // Output data from storage
      read_ptr <= read_ptr + 1;     // Advance read pointer
    end
  end

  // ✅ Counter Logic —> Tracks occupancy synchronously
  always @(posedge clk) begin
    if (rst) begin
      count <= 0;
    end else begin
      case ({wr_en && !full, rd_en && !empty})
        2'b10: count <= count + 1;   // Write only
        2'b01: count <= count - 1;   // Read only
        default: count <= count;     // Idle or both (write & read same cycle)
      endcase
    end
  end

  // ✅ Status Flags —> Sequentially update flags
  always @(posedge clk) begin
    if (rst) begin
      full <= 0;
      empty <= 1;
    end else begin
      full <= (count == DEPTH);
      empty <= (count == 0);
    end
  end

endmodule

fifo_sync_tb.v
`timescale 1ns/1ps

module fifo_sync_tb;

  parameter DATA_WIDTH = 8;
  parameter DEPTH = 16;
  parameter ADDR_WIDTH = 4;

  // DUT I/O
  reg clk;
  reg rst;
  reg wr_en;
  reg rd_en;
  reg [DATA_WIDTH-1:0] din;
  wire [DATA_WIDTH-1:0] dout;
  wire full;
  wire empty;

  // Instantiate DUT
  fifo_sync #(
    .DATA_WIDTH(DATA_WIDTH),
    .DEPTH(DEPTH),
    .ADDR_WIDTH(ADDR_WIDTH)
  ) uut (
    .clk(clk),
    .rst(rst),
    .wr_en(wr_en),
    .rd_en(rd_en),
    .din(din),
    .dout(dout),
    .full(full),
    .empty(empty)
  );

  // Clock
  initial clk = 0;
  always #5 clk = ~clk;

  // Stimulus
  initial begin
    $dumpfile("fifo.vcd");
    $dumpvars(0, fifo_sync_tb);

    rst = 1; wr_en = 0; rd_en = 0; din = 0;

    #20 rst = 0;

    // Write 5 data
    repeat (5) begin
      @(posedge clk);
      wr_en = 1;
      din = $random % 256;
    end
    @(posedge clk);
    wr_en = 0;

    #20;

    // Read 5 data
    repeat (5) begin
      @(posedge clk);
      rd_en = 1;
    end
    @(posedge clk);
    rd_en = 0;

    #50 $finish;
  end

  initial begin
    $monitor("T=%0t wr_en=%b din=%h rd_en=%b dout=%h full=%b empty=%b",
      $time, wr_en, din, rd_en, dout, full, empty);
  end

endmodule

fifo.vcd
$date
	Tue Jul 01 12:51:02 2025
$end
$version
	Icarus Verilog
$end
$timescale
	1ps
$end
$scope module fifo_sync_tb $end
$var wire 1 ! full $end
$var wire 1 " empty $end
$var wire 8 # dout [7:0] $end
$var parameter 32 $ ADDR_WIDTH $end
$var parameter 32 % DATA_WIDTH $end
$var parameter 32 & DEPTH $end
$var reg 1 ' clk $end
$var reg 8 ( din [7:0] $end
$var reg 1 ) rd_en $end
$var reg 1 * rst $end
$var reg 1 + wr_en $end
$scope module uut $end
$var wire 1 ' clk $end
$var wire 8 , din [7:0] $end
$var wire 1 ) rd_en $end
$var wire 1 * rst $end
$var wire 1 + wr_en $end
$var parameter 32 - ADDR_WIDTH $end
$var parameter 32 . DATA_WIDTH $end
$var parameter 32 / DEPTH $end
$var reg 5 0 count [4:0] $end
$var reg 8 1 dout [7:0] $end
$var reg 1 " empty $end
$var reg 1 ! full $end
$var reg 4 2 read_ptr [3:0] $end
$var reg 4 3 write_ptr [3:0] $end
$upscope $end
$upscope $end
$enddefinitions $end
$comment Show the parameter values. $end
$dumpall
b10000 /
b1000 .
b100 -
b10000 &
b1000 %
b100 $
$end
#0
$dumpvars
bx 3
bx 2
bx 1
bx 0
b0 ,
0+
1*
0)
b0 (
0'
bx #
x"
x!
$end
#5000
b0 3
b0 2
b0 #
b0 1
b0 0
1"
0!
1'
#10000
0'
#15000
1'
#20000
0'
0*
#25000
b1 3
b1 0
b100100 (
b100100 ,
1+
1'
#30000
0'
#35000
0"
b10 0
b10 3
b10000001 (
b10000001 ,
1'
#40000
0'
#45000
b11 3
b11 0
b1001 (
b1001 ,
1'
#50000
0'
#55000
b100 0
b100 3
b1100011 (
b1100011 ,
1'
#60000
0'
#65000
b101 3
b101 0
b1101 (
b1101 ,
1'
#70000
0'
#75000
b110 0
b110 3
0+
1'
#80000
0'
#85000
1'
#90000
0'
#95000
b101 0
b1 2
b100100 #
b100100 1
1)
1'
#100000
0'
#105000
b10 2
b100 0
1'
#110000
0'
#115000
b11 0
b11 2
b1001 #
b1001 1
1'
#120000
0'
#125000
b100 2
b10 0
1'
#130000
0'
#135000
b1 0
b101 2
b1101 #
b1101 1
1'
#140000
0'
#145000
b110 2
b0 0
0)
1'
#150000
0'
#155000
1"
1'
